deepgis_utils/__init__.py
deepgis_utils/auth.py
deepgis_utils/exceptions.py
deepgis_utils/importer.py
deepgis_utils/publisher.py
deepgis_utils/utils.py
deepgis_utils-0.1.2.dist-info/LICENSE
deepgis_utils-0.1.2.dist-info/WHEEL
deepgis_utils-0.1.2.dist-info/METADATA
deepgis_utils-0.1.2.dist-info/RECORD
