Metadata-Version: 2.1
Name: deepgis-utils
Version: 0.1.2
Summary: A collection of utilities for DeepGIS
Home-page: https://github.com/Rainlv/DeepGIS-utils
License: MIT
Author: Xuanh.W
Author-email: Xuanh.W.coding@outlook.com
Requires-Python: >=3.9,<4.0
Classifier: License :: OSI Approved :: MIT License
Classifier: Programming Language :: Python :: 3
Classifier: Programming Language :: Python :: 3.10
Classifier: Programming Language :: Python :: 3.9
Requires-Dist: GeoAlchemy2 (>=0.11.1,<0.12.0)
Requires-Dist: SQLAlchemy (>=1.4.35,<1.5.0)
Requires-Dist: geopandas (>=0.10.2,<0.11.0)
Requires-Dist: psycopg2 (>=2.9.3,<2.10.0)
Requires-Dist: requests (>=2.27.1,<2.28.0)
Project-URL: Repository, https://github.com/Rainlv/DeepGIS-utils
